control_unit.v
module control_unit (
    input wire [3:0] opcode,
    input wire cf,
    input wire sf,
    input wire zf,
    output wire imm_sel,
    output wire reg_en,
    output wire [1:0] op,
    output wire jmp_sel
);
wire _jmp,_je,_or;
assign imm_sel = ~opcode[3] & opcode[2];
assign reg_en = ~(opcode[3] & ~opcode[2]);
assign op = {opcode[1],opcode[0]};
assign _jmp = ~opcode[1] & ~opcode[0];
assign _je = ~sf & zf & ~opcode[1] & opcode[0];
assign _or = _jmp | _je;
assign jmp_sel = ~reg_en & _or;
endmodule

control_unit_tb.v
`timescale 1ns/1ps
`include "control_unit.v"
module control_unit_tb;
    reg [3:0] opcode;
    reg cf,sf,zf;
    wire [1:0] op;
    wire imm_sel,reg_en,jmp_sel;
    control_unit uut(opcode,cf,sf,zf,imm_sel,reg_en,op,jmp_sel);
    initial begin
        opcode <= 4'b0000;
        cf <= 1'b0;
        sf <= 1'b0;
        zf <= 1'b0;
        #20;
        opcode <= 4'b0000;
        #20;
        opcode <= 4'b0001;
        #20;
        opcode <= 4'b0100;
        #20;
        opcode <= 4'b0101;
        #20;
        opcode <= 4'b1000;
        #20;
        opcode <= 4'b1001;
        #20;
        opcode <= 4'b1001;
        zf <= 1'b1;
        #20;
        sf <= 1'b1;
        #20;
        zf <= 1'b0;
        $finish;
    end
    initial begin
        $dumpfile("control_unit.vcd");
        $dumpvars(0, control_unit_tb);
        $monitor("opcode=%b op=%b imm_sel=%b reg_en=%b jmp_sel=%b\ncf=%b sf=%b zf=%b",opcode,op,imm_sel,reg_en,jmp_sel,cf,sf,zf);
    end
endmodule

control_unit.vcd
$date
	Mon Apr 10 02:40:24 2023
$end
$version
	Icarus Verilog
$end
$timescale
	1ps
$end
$scope module control_unit_tb $end
$var wire 1 ! reg_en $end
$var wire 2 " op [1:0] $end
$var wire 1 # jmp_sel $end
$var wire 1 $ imm_sel $end
$var reg 1 % cf $end
$var reg 4 & opcode [3:0] $end
$var reg 1 ' sf $end
$var reg 1 ( zf $end
$scope module uut $end
$var wire 1 ) _je $end
$var wire 1 * _jmp $end
$var wire 1 + _or $end
$var wire 1 % cf $end
$var wire 1 $ imm_sel $end
$var wire 1 # jmp_sel $end
$var wire 4 , opcode [3:0] $end
$var wire 1 ! reg_en $end
$var wire 1 ' sf $end
$var wire 1 ( zf $end
$var wire 2 - op [1:0] $end
$upscope $end
$upscope $end
$enddefinitions $end
#0
$dumpvars
b0 -
b0 ,
1+
1*
0)
0(
0'
b0 &
0%
0$
0#
b0 "
1!
$end
#40000
0+
0*
b1 "
b1 -
b1 &
b1 ,
#60000
1+
1*
1$
b0 "
b0 -
b100 &
b100 ,
#80000
0+
0*
b1 "
b1 -
b101 &
b101 ,
#100000
1#
1+
0!
1*
0$
b0 "
b0 -
b1000 &
b1000 ,
#120000
0#
0+
0*
b1 "
b1 -
b1001 &
b1001 ,
#140000
1#
1+
1)
1(
#160000
0#
0+
0)
1'
#180000
0(
